mouc/__init__.py
mouc/__main__.py
mouc/backends/__init__.py
mouc/backends/base.py
mouc/backends/docx.py
mouc/backends/markdown.py
mouc/backends/text_formatter.py
mouc/builtin_gantt.py
mouc/cli.py
mouc/context.py
mouc/document.py
mouc/exceptions.py
mouc/gantt.py
mouc/graph.py
mouc/jira_cli.py
mouc/jira_client.py
mouc/jira_config.py
mouc/jira_interactive.py
mouc/jira_report.py
mouc/jira_sync.py
mouc/loader.py
mouc/logger.py
mouc/models.py
mouc/netrc_utils.py
mouc/parser.py
mouc/py.typed
mouc/report_cli.py
mouc/resources.py
mouc/rust.cpython-312-x86_64-linux-gnu.so
mouc/rust.pyi
mouc/scheduler/__init__.py
mouc/scheduler/algorithms/__init__.py
mouc/scheduler/algorithms/bounded_rollout.py
mouc/scheduler/algorithms/cpsat.py
mouc/scheduler/algorithms/parallel_sgs.py
mouc/scheduler/algorithms/rust_adapter.py
mouc/scheduler/config.py
mouc/scheduler/core.py
mouc/scheduler/lock.py
mouc/scheduler/preprocessors/__init__.py
mouc/scheduler/preprocessors/backward_pass.py
mouc/scheduler/protocols.py
mouc/scheduler/resources.py
mouc/scheduler/service.py
mouc/scheduler/timeframes.py
mouc/scheduler/validator.py
mouc/schemas.py
mouc/styling.py
mouc/unified_config.py
mouc/workflows/__init__.py
mouc/workflows/stdlib.py
mouc-0.7.4.dist-info/METADATA
mouc-0.7.4.dist-info/WHEEL
mouc-0.7.4.dist-info/entry_points.txt
mouc-0.7.4.dist-info/licenses/LICENSE
mouc-0.7.4.dist-info/RECORD
