Metadata-Version: 2.4
Name: mouc
Version: 0.7.4
Classifier: Development Status :: 3 - Alpha
Classifier: Intended Audience :: Developers
Classifier: Intended Audience :: System Administrators
Classifier: Topic :: Software Development :: Libraries :: Python Modules
Classifier: Topic :: Software Development :: Documentation
Classifier: Topic :: Utilities
Classifier: Programming Language :: Python :: 3
Classifier: Programming Language :: Python :: 3.10
Classifier: Programming Language :: Python :: 3.11
Classifier: Programming Language :: Python :: 3.12
Classifier: Operating System :: OS Independent
Classifier: Typing :: Typed
Requires-Dist: pyyaml>=6.0
Requires-Dist: ruamel-yaml>=0.18.0
Requires-Dist: graphviz>=0.20
Requires-Dist: pydantic>=2.0
Requires-Dist: typer>=0.9.0
Requires-Dist: atlassian-python-api>=3.41.0
Requires-Dist: python-dotenv>=1.0.0
Requires-Dist: python-docx>=1.1.0
Requires-Dist: mistune>=3.0
Requires-Dist: ortools>=9.8
Requires-Dist: pytest>=7.0 ; extra == 'dev'
Requires-Dist: pytest-cov>=4.0 ; extra == 'dev'
Requires-Dist: ruff>=0.1.0 ; extra == 'dev'
Requires-Dist: pyright>=1.1.407 ; extra == 'dev'
Requires-Dist: build>=1.0.0 ; extra == 'dev'
Requires-Dist: twine>=5.0.0 ; extra == 'dev'
Provides-Extra: dev
License-File: LICENSE
Summary: A YAML-based dependency tracker and automatic scheduler for project roadmaps
Keywords: dependency-tracking,project-management,capability-mapping,user-stories,technical-dependencies,outcome-mapping,software-planning,visualization,yaml-based
Author-email: Randall Nortman <oss@randallnortman.net>
License-Expression: MIT
Requires-Python: >=3.10
Project-URL: Documentation, https://github.com/rnortman/mouc#readme
Project-URL: Homepage, https://github.com/rnortman/mouc
Project-URL: Issues, https://github.com/rnortman/mouc/issues
Project-URL: Repository, https://github.com/rnortman/mouc.git
